iodproxy/__init__.py
iodproxy/cli.py
iodproxy/logger.py
iodproxy/proxy.py
iodproxy-0.2.6.dist-info/METADATA
iodproxy-0.2.6.dist-info/WHEEL
iodproxy-0.2.6.dist-info/entry_points.txt
iodproxy-0.2.6.dist-info/licenses/LICENSE
iodproxy-0.2.6.dist-info/RECORD
