Metadata-Version: 2.4
Name: iodproxy
Version: 0.2.6
Summary: A proxy for IOD MCP servers
License-File: LICENSE
Requires-Python: >=3.12
Requires-Dist: logfire>=2.11.1
Requires-Dist: omproxy>=0.3.0
